LICENSE
README.md
setup.py
yasiu/__init__.py
yasiu/visualisation.py
yasiu.visualisation.egg-info/PKG-INFO
yasiu.visualisation.egg-info/SOURCES.txt
yasiu.visualisation.egg-info/dependency_links.txt
yasiu.visualisation.egg-info/requires.txt
yasiu.visualisation.egg-info/top_level.txt